freckles/__init__.py
freckles/defaults.py
freckles/exceptions.py
freckles/frecklecutable.py
freckles/freckles.py
freckles/frkl.info
freckles/output_callback.py
freckles/schemas.py
freckles/adapters/__init__.py
freckles/adapters/adapters.py
freckles/adapters/freckles/__init__.py
freckles/adapters/freckles/freckles_adapter_freckles.py
freckles/context/__init__.py
freckles/context/config.py
freckles/context/freckles_context.py
freckles/context/run_config.py
freckles/doc/dev.md
freckles/doc/getting_started.md
freckles/doc/glossary.md
freckles/doc/installation.md
freckles/doc/overview.md
freckles/doc/running_frecklets.md
freckles/doc/security.md
freckles/doc/adapters/index.md
freckles/doc/adapters/nsbl.md
freckles/doc/configuration/contexts.md
freckles/doc/configuration/index.md
freckles/doc/configuration/repositories.md
freckles/doc/configuration/settings.md
freckles/doc/frecklets/anatomy.md
freckles/doc/frecklets/evolution.md
freckles/doc/frecklets/index.md
freckles/doc/frecklets/resources.md
freckles/doc/interfaces/cli.md
freckles/doc/interfaces/index.md
freckles/doc/interfaces/python.md
freckles/external/docs/unlock_config_text.md
freckles/external/freckles_frecklets/frecklecute.frecklet
freckles/external/freql/frecklets.graphql
freckles/external/scripts/freckle_folders.sh
freckles/external/scripts/freckles_facts.sh
freckles/frecklet/__init__.py
freckles/frecklet/arguments.py
freckles/frecklet/describe.py
freckles/frecklet/doc.py
freckles/frecklet/frecklet.py
freckles/frecklet/tasks.py
freckles/frecklet/vars.py
freckles/interfaces/__init__.py
freckles/interfaces/freql.py
freckles/templates/cnf_doc/html/layout.md.j2
freckles/templates/cnf_doc/markdown/layout.md.j2
freckles/templates/frecklet_doc/html/code.html
freckles/templates/frecklet_doc/html/examples.html
freckles/templates/frecklet_doc/html/layout.html
freckles/templates/frecklet_doc/html/variables.html
freckles/templates/frecklet_doc/html_old/command-line.html
freckles-1.0.0.dist-info/AUTHORS.rst
freckles-1.0.0.dist-info/LICENSE
freckles-1.0.0.dist-info/METADATA
freckles-1.0.0.dist-info/WHEEL
freckles-1.0.0.dist-info/entry_points.txt
freckles-1.0.0.dist-info/top_level.txt
freckles-1.0.0.dist-info/RECORD
